alphagram/__init__.py
alphagram/enums.py
alphagram/methods.py
alphagram/types.py
alphagram-1.0.0.dist-info/LICENSE
alphagram-1.0.0.dist-info/METADATA
alphagram-1.0.0.dist-info/WHEEL
alphagram-1.0.0.dist-info/top_level.txt
alphagram-1.0.0.dist-info/RECORD
